matrixone/__init__.py
matrixone/account.py
matrixone/async_client.py
matrixone/async_orm.py
matrixone/base_client.py
matrixone/cdc.py
matrixone/cli_tools.py
matrixone/client.py
matrixone/clone.py
matrixone/config.py
matrixone/connection_hooks.py
matrixone/exceptions.py
matrixone/export.py
matrixone/fulltext_manager.py
matrixone/index_utils.py
matrixone/load_data.py
matrixone/logger.py
matrixone/metadata.py
matrixone/moctl.py
matrixone/orm.py
matrixone/pitr.py
matrixone/pubsub.py
matrixone/restore.py
matrixone/search_vector_index.py
matrixone/session.py
matrixone/snapshot.py
matrixone/sql_builder.py
matrixone/sqlalchemy_select.py
matrixone/stage.py
matrixone/vector_manager.py
matrixone/version.py
matrixone/sqlalchemy_ext/__init__.py
matrixone/sqlalchemy_ext/dialect.py
matrixone/sqlalchemy_ext/fulltext_index.py
matrixone/sqlalchemy_ext/fulltext_search.py
matrixone/sqlalchemy_ext/hnsw_config.py
matrixone/sqlalchemy_ext/ivf_config.py
matrixone/sqlalchemy_ext/json_functions.py
matrixone/sqlalchemy_ext/json_type.py
matrixone/sqlalchemy_ext/snapshot.py
matrixone/sqlalchemy_ext/table_builder.py
matrixone/sqlalchemy_ext/vector_index.py
matrixone/sqlalchemy_ext/vector_type.py
matrixone_python_sdk-0.1.11.dist-info/licenses/LICENSE
tests/__init__.py
tests/offline/__init__.py
tests/offline/conftest.py
tests/offline/test_account.py
tests/offline/test_async_client_query_comprehensive.py
tests/offline/test_basic.py
tests/offline/test_case_sensitivity.py
tests/offline/test_cdc_sql.py
tests/offline/test_connection_hooks_offline.py
tests/offline/test_dialect_schema_handling.py
tests/offline/test_explain_methods.py
tests/offline/test_filter_logical_in.py
tests/offline/test_fulltext_search_comprehensive.py
tests/offline/test_ivf_config.py
tests/offline/test_join_methods.py
tests/offline/test_join_sqlalchemy_compatibility.py
tests/offline/test_json_offline.py
tests/offline/test_load_data.py
tests/offline/test_logical_in_method.py
tests/offline/test_matrixone_version_parsing.py
tests/offline/test_metadata_offline.py
matrixone_python_sdk-0.1.11.dist-info/METADATA
matrixone_python_sdk-0.1.11.dist-info/WHEEL
matrixone_python_sdk-0.1.11.dist-info/entry_points.txt
matrixone_python_sdk-0.1.11.dist-info/top_level.txt
matrixone_python_sdk-0.1.11.dist-info/RECORD
