Metadata-Version: 2.4
Name: matrixone-python-sdk
Version: 0.1.11
Summary: A comprehensive Python SDK for MatrixOne database operations with vector search, fulltext search, and advanced features
Home-page: https://github.com/matrixorigin/matrixone
Author: MatrixOne Team
Author-email: MatrixOne Team <dev@matrixone.io>
Maintainer-email: MatrixOne Team <dev@matrixone.io>
License: Apache-2.0
Project-URL: Homepage, https://github.com/matrixorigin/matrixone
Project-URL: Documentation, https://matrixone.readthedocs.io/
Project-URL: Repository, https://github.com/matrixorigin/matrixone
Project-URL: Issues, https://github.com/matrixorigin/matrixone/issues
Project-URL: Changelog, https://github.com/matrixorigin/matrixone/blob/main/clients/python/CHANGELOG.md
Keywords: matrixone,database,vector,search,sqlalchemy,python,diagnostic,cli,monitoring,ivf,hnsw
Classifier: Development Status :: 4 - Beta
Classifier: Intended Audience :: Developers
Classifier: License :: OSI Approved :: Apache Software License
Classifier: Operating System :: OS Independent
Classifier: Programming Language :: Python :: 3
Classifier: Programming Language :: Python :: 3.8
Classifier: Programming Language :: Python :: 3.9
Classifier: Programming Language :: Python :: 3.10
Classifier: Programming Language :: Python :: 3.11
Classifier: Programming Language :: Python :: 3.12
Classifier: Topic :: Database
Classifier: Topic :: Software Development :: Libraries :: Python Modules
Requires-Python: >=3.8
License-File: LICENSE
Requires-Dist: PyMySQL>=1.0.0
Requires-Dist: aiomysql>=0.2.0
Requires-Dist: SQLAlchemy<3.0.0,>=1.4.0
Requires-Dist: typing-extensions>=4.0.0
Requires-Dist: python-dateutil>=2.8.0
Requires-Dist: numpy>=1.20.0
Requires-Dist: prompt_toolkit>=3.0.0
Provides-Extra: dev
Requires-Dist: pytest>=6.0; extra == "dev"
Requires-Dist: pytest-asyncio>=0.18.0; extra == "dev"
Requires-Dist: pytest-cov>=3.0; extra == "dev"
Requires-Dist: Faker>=10.0.0; extra == "dev"
Requires-Dist: pyarrow>=10.0.0; extra == "dev"
Requires-Dist: black>=22.0; extra == "dev"
Requires-Dist: flake8>=4.0; extra == "dev"
Requires-Dist: mypy>=0.950; extra == "dev"
Requires-Dist: isort>=5.0; extra == "dev"
Requires-Dist: sphinx>=4.0; extra == "dev"
Requires-Dist: sphinx-rtd-theme>=1.0; extra == "dev"
Requires-Dist: sphinx-autobuild>=2021.3.14; extra == "dev"
Requires-Dist: build>=0.8.0; extra == "dev"
Requires-Dist: twine>=4.0.0; extra == "dev"
Requires-Dist: tox>=3.24.0; extra == "dev"
Provides-Extra: docs
Requires-Dist: sphinx>=4.0; extra == "docs"
Requires-Dist: sphinx-rtd-theme>=1.0; extra == "docs"
Requires-Dist: sphinx-autobuild>=2021.3.14; extra == "docs"
Provides-Extra: test
Requires-Dist: pytest>=6.0; extra == "test"
Requires-Dist: pytest-asyncio>=0.18.0; extra == "test"
Requires-Dist: pytest-cov>=3.0; extra == "test"
Requires-Dist: Faker>=10.0.0; extra == "test"
Requires-Dist: pyarrow>=10.0.0; extra == "test"
Dynamic: author
Dynamic: home-page
Dynamic: license-file
Dynamic: requires-python
